setup.py
Dory.egg-info/PKG-INFO
Dory.egg-info/SOURCES.txt
Dory.egg-info/dependency_links.txt
Dory.egg-info/entry_points.txt
Dory.egg-info/requires.txt
Dory.egg-info/top_level.txt
dory/__init__.py
dory/__main__.py
dory/backup.py
dory/dory.py
dory/util.py