Metadata-Version: 1.0
Name: Dory
Version: 0.0.4
Summary: Simple Backup
Home-page: https://github.com/inosms/dory
Author: inosms
Author-email: UNKNOWN
License: UNKNOWN
Platform: UNKNOWN
